IC design/test system/simple.v
module simple(a, b, cin, cout, sum);
	input	a, b, cin;
	output	cout, sum;

	assign	{ cout, sum } = a + b + cin;
endmodule

IC design course/test system/simple_tb.v

module simple_tb;
	reg   a, b, cin;
	wire  cout, sum;

initial
	begin
		$dumpfile("simple.vcd");
		$dumpvars(0, s);
		$monitor("a = %b, b = %b cin = %b | cout = %b sum = %b ", a, b, cin, cout, sum);
		#50 a=1'b0; b=1'b0; cin=1'b0;
		#50 a=1'b0; b=1'b1; cin=1'b0;
		#50 a=1'b1; b=1'b0; cin=1'b0;
		#50 a=1'b1; b=1'b1; cin=1'b0;
		#50 a=1'b0; b=1'b0; cin=1'b1;
		#50 a=1'b0; b=1'b1; cin=1'b1;
		#50 a=1'b1; b=1'b0; cin=1'b1;
		#50 a=1'b1; b=1'b1; cin=1'b1;
		#50 $finish;
	end

	simple s( a, b, cin, cout, sum );
endmodule

IC design/test system/simple.vcd
$date
	Thu Mar 23 18:48:25 2023
$end
$version
	Icarus Verilog
$end
$timescale
	1s
$end
$scope module simple_tb $end
$scope module s $end
$var wire 1 ! a $end
$var wire 1 " b $end
$var wire 1 # cin $end
$var wire 1 $ sum $end
$var wire 1 % cout $end
$upscope $end
$upscope $end
$enddefinitions $end
$comment Show the parameter values. $end
$dumpall
$end
#0
$dumpvars
x%
x$
x#
x"
x!
$end
#50
0$
0%
0#
0"
0!
#100
1$
1"
#150
0"
1!
#200
0$
1%
1"
#250
1$
0%
1#
0"
0!
#300
0$
1%
1"
#350
0"
1!
#400
1$
1"
