IC design course/homework/question/HW2/rails_state.v
module rails(clk, reset, data, valid, result);

input        clk;
input        reset;
input  [3:0] data;
output reg  valid;
output reg  result; 
reg [3:0] data_arr [0:9];
reg [9:0] station_order, B_order, temp_wire;
reg [2:0] state_reg, state_next;
reg [3:0] train_num, train_idx, read_idx, train;
parameter [2:0] IDLE=3'd0, FETCH_FIRST=3'd1, FETCH=3'd2, CAL=3'd3, FINISH=3'd4;
// wire [9:0]temp_wire;
integer i;

always@(posedge clk)
begin 
    if(reset)begin
        state_reg <= FETCH_FIRST;
    end
    else 
    begin
        state_reg <= state_next;
    end
end

always@(*)
begin
    case (state_reg)
        IDLE:
        begin
            // if(data)    state_next = FETCH_FIRST;
            // else    state_next = IDLE;
            state_next = FETCH_FIRST;
        end
        FETCH_FIRST:
        begin
            state_next = FETCH;
        end
        FETCH:
        begin
            if(train_idx < train_num - 1) state_next = FETCH ;
            else state_next = CAL;
        end
        CAL:
            if(read_idx < train_num-1) state_next = CAL;
            else state_next = FINISH;
        default:
        begin 
            state_next = IDLE;
        end
    endcase
end

// assign temp_wire = (data)?((10'b1 << (data-1))-1):10'b0 ;

always@(posedge clk or posedge reset)
begin
    if(reset)
    begin
        result = 1'b1;
        valid = 1'b0;
        station_order = 10'b0;
        B_order = 10'b0;
        train_num = 4'b0;
        train_idx = 4'b0;
        read_idx = 4'b0;
        for(i = 0; i < 10; i = i + 1) data_arr[i] = 4'b0;
    end
    else
    begin
        case (state_reg)
            IDLE:
            begin
                result = 1'b1;
                valid = 1'b0;
                station_order = 10'b0;
                B_order = 10'b0;
                train_num = 4'b0;
                train_idx = 4'b0;
                read_idx = 4'b0;
                for(i = 0; i < 10; i = i + 1) data_arr[i] = 4'b0;
            end
            FETCH_FIRST:
            begin
                train_num = data;
            end
            FETCH:
            begin
                data_arr[train_idx] = data;
                train_idx = train_idx + 4'b1;
            end
            CAL:
            begin
                train = data_arr[read_idx];
                read_idx = read_idx + 1;
                temp_wire = (10'b1 << (train-1))-1;
                if((temp_wire > station_order))
                    station_order = temp_wire ^ B_order;								
                else
                begin
                    if((temp_wire << 1)+1 >= station_order)    station_order[train-1] = 1'b0;
                    else    result = 1'b0;                    
                end
                B_order[(train-1)] = 1'b1;
            end
            default:
            begin
                valid = 1'b1;
            end
        endcase
    end
end

endmodule

IC design/homework/question/HW2/tb.v
`timescale 1ns/10ps
`define CYCLE      50.0  
`define End_CYCLE  1000000000
`define PATTERN    "test_data_rails.dat"
`define EXPECT     "golden_data_rails.dat"

module testfixture();
parameter TEST_N_PAT = 100;

integer fd;
integer fg;
integer golden_result;
integer charcount;
integer pass=0;
integer fail=0;
integer pattern_count=0;

reg [3:0] data;
reg clk = 0;
wire valid;
reg reset =0;
wire result;

rails u_rails(.clk(clk),
        .reset(reset),
        .data(data),
        .valid(valid),
        .result(result));

always begin #(`CYCLE/2) clk = ~clk; end

initial begin
    $dumpfile("rails.vcd");
	$dumpvars(0, u_rails);
    $display("----------------------");
    $display("-- Simulation Start --");
    $display("----------------------");
    @(posedge clk);  #2 reset = 1'b1; 
    #(`CYCLE*2);  
    @(posedge clk);  #2  reset = 1'b0;
end

reg [31:0] cycle=0;

always @(posedge clk) begin
    cycle=cycle+1;
    if (cycle > `End_CYCLE) begin
        $display("--------------------------------------------------");
        $display("-- Failed waiting valid signal, Simulation STOP --");
        $display("--------------------------------------------------");
        $fclose(fd);
        $finish;
    end
end

initial begin
    fd = $fopen(`PATTERN,"r");
    if (fd == 0) begin
        $display ("pattern handle null");
        $finish;
    end
end

initial begin
    fg = $fopen(`EXPECT,"r");
    if (fg == 0) begin
        $display ("golden handle null");
        $finish;
    end
end

// reg  valid_reg;
// always @(posedge clk) begin
//     valid_reg = valid;
// end
reg wait_valid;
reg get_result;
reg first;
reg [3:0] num;
integer in_count;

always @(posedge clk ) begin
    if (reset) begin
        wait_valid=0;
    end
    else begin
        if(wait_valid == 0) begin
            if(in_count == num) wait_valid =1;
        end
        else begin
            if (valid ==1) begin
                wait_valid=0;
                get_result=result;
                charcount = $fscanf(fg, "%d", golden_result);
                if(get_result == golden_result) begin
                    pass = pass +1;
                    $display("Pattern%0d: Expect= %1d Get= %d, PASS\n",pattern_count,golden_result,get_result);
                end
                else begin
                    fail = fail +1;
                    $display("Pattern%0d: Expect= %1d Get= %d, FAIL\n",pattern_count,golden_result,get_result);
                end
                pattern_count = pattern_count + 1;
            end
        end
    end
end

always @(negedge clk ) begin
    if (reset) begin
        in_count = 0;
        first = 1;
    end 
    else begin
        if (pattern_count < TEST_N_PAT) begin
            if(wait_valid ==0) begin
                if(first) begin
                    first = 0;
                    charcount = $fscanf(fd, "%d", num);
                    data = num;
                end
                else begin
                    charcount = $fscanf(fd, "%d", data);
                    in_count = in_count + 1;    
                end
            end
            else begin
                data = 4'dx;
                first = 1;
                in_count = 0;
            end
        end //if (!$feof(fd)) begin
        else begin
             $fclose(fd);
             $display ("-----------------------------------------------------------");
             if(fail == 0)
                 $display("----    Simulation finish,  ALL PASS,  Score = %2d     ----", pass);
             else
                 $display("-- Simulation finish,  Pass = %2d , Fail = %2d, Score = %2d --",pass,fail,pass);
             $display ("-----------------------------------------------------------");
             $finish;
        end
    end
end
endmodule

IC design/homework/question/HW2/rails.vcd
$date
	Tue Apr 18 19:35:21 2023
$end
$version
	ModelSim Version 2020.1
$end
$timescale
	10ps
$end

$scope module testfixture $end

$scope module u_rails $end
$var parameter 3 ! IDLE $end
$var parameter 3 " FETCH_FIRST $end
$var parameter 3 # FETCH $end
$var parameter 3 $ CAL $end
$var parameter 3 % FINISH $end
$var wire 1 & clk $end
$var wire 1 ' reset $end
$var wire 1 ( data [3] $end
$var wire 1 ) data [2] $end
$var wire 1 * data [1] $end
$var wire 1 + data [0] $end
$var reg 1 , valid $end
$var reg 1 - result $end
$var reg 10 . station_order [9:0] $end
$var reg 10 / B_order [9:0] $end
$var reg 10 0 temp_wire [9:0] $end
$var reg 3 1 state_reg [2:0] $end
$var reg 3 2 state_next [2:0] $end
$var reg 4 3 train_num [3:0] $end
$var reg 4 4 train_idx [3:0] $end
$var reg 4 5 read_idx [3:0] $end
$var reg 4 6 train [3:0] $end
$var integer 32 7 i $end
$upscope $end
$upscope $end
$enddefinitions $end
#0
$dumpvars
x,
x-
bx .
bx /
bx 0
bx 1
bx 2
bx 3
bx 4
bx 5
bx 6
b0 !
b1 "
b10 #
b11 $
b100 %
bx 7
x+
x*
x)
x(
0'
0&
$end
#2500
1&
1,
#2700
1'
1-
0,
b0 .
b0 /
b0 3
b0 4
b0 5
b0 7
b1 7
b10 7
b11 7
b100 7
b101 7
b110 7
b111 7
b1000 7
b1001 7
b1010 7
b0 2
#5000
0&
#7500
1&
b0 7
b1 7
b10 7
b11 7
b100 7
b101 7
b110 7
b111 7
b1000 7
b1001 7
b1010 7
b1 1
b10 2
#10000
0&
#12500
1&
b0 7
b1 7
b10 7
b11 7
b100 7
b101 7
b110 7
b111 7
b1000 7
b1001 7
b1010 7
#15000
0&
#17500
1&
b0 7
b1 7
b10 7
b11 7
b100 7
b101 7
b110 7
b111 7
b1000 7
b1001 7
b1010 7
#17700
0'
#20000
0&
0+
1*
1)
0(
#22500
1&
b110 3
b10 1
#25000
0&
0)
#27500
1&
b1 4
#30000
0&
0*
1)
#32500
1&
b10 4
#35000
0&
1+
0)
#37500
1&
b11 4
#40000
0&
1*
#42500
1&
b100 4
#45000
0&
0+
1)
#47500
1&
b101 4
b11 2
#50000
0&
1+
0*
#52500
1&
b110 4
b11 1
#55000
0&
x+
x*
x)
x(
#57500
1&
b10 6
b1 5
b1 0
b1 .
b10 /
#60000
0&
#62500
1&
b100 6
b10 5
b111 0
b101 .
b1010 /
#65000
0&
#67500
1&
b1 6
b11 5
b0 0
0-
b1011 /
#70000
0&
#72500
1&
b11 6
b100 5
b11 0
b1 .
b1111 /
#75000
0&
#77500
1&
b110 6
b101 5
b11111 0
b10000 .
b101111 /
b100 2
#80000
0&
#82500
1&
b101 6
b110 5
b1111 0
b0 .
b111111 /
b100 1
b0 2
#85000
0&
#87500
1&
1,
b0 1
b1 2
#90000
0&
#92500
1&
1-
0,
b0 /
b0 3
b0 4
b0 5
b0 7
b1 7
b10 7
b11 7
b100 7
b101 7
b110 7
b111 7
b1000 7
b1001 7
b1010 7
b1 1
b10 2
#95000
0&
1+
1*
1)
0(
#97500
1&
b111 3
b10 1
#100000
0&
0*
#102500
1&
b1 4
#105000
0&
0+
#107500
1&
b10 4
#110000
0&
1*
#112500
1&
b11 4
#115000
0&
1+
0)
#117500
1&
b100 4
#120000
0&
0*
#122500
1&
b101 4
#125000
0&
0+
1*
#127500
1&
b110 4
b11 2
#130000
0&
1+
1)
#132500
1&
b111 4
b11 1
#135000
0&
x+
x*
x)
x(
#137500
1&
b1 5
b1111 .
b10000 /
#140000
0&
#142500
1&
b100 6
b10 5
b111 0
b111 .
b11000 /
#145000
0&
#147500
1&
b110 6
b11 5
b11111 0
b111000 /
#150000
0&
#152500
1&
b11 6
b100 5
b11 0
b11 .
b111100 /
#155000
0&
#157500
1&
b1 6
b101 5
b0 0
0-
b111101 /
#160000
0&
#162500
1&
b10 6
b110 5
b1 0
b1 .
b111111 /
b100 2
#165000
0&
#167500
1&
b111 6
b111 5
b111111 0
b0 .
b1111111 /
b100 1
b0 2
#170000
0&
#172500
1&
1,
b0 1
b1 2
#175000
0&
#177500
1&
1-
0,
b0 /
b0 3
b0 4
b0 5
b0 7
b1 7
b10 7
b11 7
b100 7
b101 7
b110 7
b111 7
b1000 7
b1001 7
b1010 7
b1 1
b10 2
#180000
0&
0+
1*
1)
0(
#182500
1&
b110 3
b10 1
#185000
0&
0*
#187500
1&
b1 4
#190000
0&
1*
0)
#192500
1&
b10 4
#195000
0&
1+
0*
#197500
1&
b11 4
#200000
0&
0+
1*
1)
#202500
1&
b100 4
#205000
0&
1+
0*
#207500
1&
b101 4
b11 2
#210000
0&
1*
0)
#212500
1&
b110 4
b11 1
#215000
0&
x+
x*
x)
x(
#217500
1&
b100 6
b1 5
b111 0
b111 .
b1000 /
#220000
0&
#222500
1&
b10 6
b10 5
b1 0
0-
b1010 /
#225000
0&
#227500
1&
b1 6
b11 5
b0 0
b1011 /
#230000
0&
#232500
1&
b110 6
b100 5
b11111 0
b10100 .
b101011 /
#235000
0&
#237500
1&
b101 6
b101 5
b1111 0
b100 .
b111011 /
b100 2
#240000
0&
#242500
1&
b11 6
b110 5
b11 0
b0 .
b111111 /
b100 1
b0 2
#245000
0&
#247500
1&
1,
b0 1
b1 2
#250000
0&
#252500
1&
1-
0,
b0 /
b0 3
b0 4
b0 5
b0 7
b1 7
b10 7
b11 7
b100 7
b101 7
b110 7
b111 7
b1000 7
b1001 7
b1010 7
b1 1
b10 2
#255000
0&
1+
0*
1)
0(
#257500
1&
b101 3
b10 1
#260000
0&
0+
#262500
1&
b1 4
#265000
0&
1+
1*
0)
#267500
1&
b10 4
#270000
0&
0+
#272500
1&
b11 4
#275000
0&
1+
0*
1)
#277500
1&
b100 4
b11 2
#280000
0&
0)
#282500
1&
b101 4
b11 1
#285000
0&
x+
x*
x)
x(
#287500
1&
b100 6
b1 5
b111 0
b111 .
b1000 /
#290000
0&
#292500
1&
b11 6
b10 5
b11 0
b11 .
b1100 /
#295000
0&
#297500
1&
b10 6
b11 5
b1 0
b1 .
b1110 /
#300000
0&
#302500
1&
b101 6
b100 5
b1111 0
b11110 /
b100 2
#305000
0&
#307500
1&
b1 6
b101 5
b0 0
b0 .
b11111 /
b100 1
b0 2
#310000
0&
#312500
1&
1,
b0 1
b1 2
#315000
0&
#317500
1&
0,
b0 /
b0 3
b0 4
b0 5
b0 7
b1 7
b10 7
b11 7
b100 7
b101 7
b110 7
b111 7
b1000 7
b1001 7
b1010 7
b1 1
b10 2
#320000
0&
0+
0*
0)
1(
#322500
1&
b1000 3
b10 1
#325000
0&
1+
1*
0(
#327500
1&
b1 4
#330000
0&
0+
#332500
1&
b10 4
#335000
0&
1+
0*
#337500
1&
b11 4
#340000
0&
0+
1(
#342500
1&
b100 4
#345000
0&
1+
1)
0(
#347500
1&
b101 4
#350000
0&
1*
#352500
1&
b110 4
#355000
0&
0+
#357500
1&
b111 4
b11 2
#360000
0&
0*
#362500
1&
b1000 4
b11 1
#365000
0&
x+
x*
x)
x(
#367500
1&
b11 6
b1 5
b11 0
b11 .
b100 /
#370000
0&
#372500
1&
b10 6
b10 5
b1 0
b1 .
b110 /
#375000
0&
#377500
1&
b1 6
b11 5
b0 0
b0 .
b111 /
#380000
0&
#382500
1&
b1000 6
b100 5
b1111111 0
b1111000 .
b10000111 /
#385000
0&
#387500
1&
b101 6
b101 5
b1111 0
0-
b10010111 /
#390000
0&
#392500
1&
b111 6
b110 5
b111111 0
b111000 .
b11010111 /
#395000
0&
#397500
1&
b110 6
b111 5
b11111 0
b11000 .
b11110111 /
b100 2
#400000
0&
#402500
1&
b100 6
b1000 5
b111 0
b11111111 /
b100 1
b0 2
#405000
0&
#407500
1&
1,
b0 1
b1 2
#410000
0&
#412500
1&
1-
0,
b0 .
b0 /
b0 3
b0 4
b0 5
b0 7
b1 7
b10 7
b11 7
b100 7
b101 7
b110 7
b111 7
b1000 7
b1001 7
b1010 7
b1 1
b10 2
#415000
0&
0+
0*
1)
0(
#417500
1&
b100 3
b10 1
#420000
0&
1+
0)
#422500
1&
b1 4
#425000
0&
1*
#427500
1&
b10 4
#430000
0&
0+
#432500
1&
b11 4
b11 2
#435000
0&
0*
1)
#437500
1&
b100 4
b11 1
#440000
0&
x+
x*
x)
x(
#442500
1&
b1 6
b1 5
b0 0
b1 /
#445000
0&
#447500
1&
b11 6
b10 5
b11 0
b10 .
b101 /
#450000
0&
#452500
1&
b10 6
b11 5
b1 0
b0 .
b111 /
b100 2
#455000
0&
#457500
1&
b100 6
b100 5
b111 0
b1111 /
b100 1
b0 2
#460000
0&
#462500
1&
1,
b0 1
b1 2
#465000
0&
#467500
1&
0,
b0 /
b0 3
b0 4
b0 5
b0 7
b1 7
b10 7
b11 7
b100 7
b101 7
b110 7
b111 7
b1000 7
b1001 7
b1010 7
b1 1
b10 2
#470000
0&
1+
0*
0)
1(
#472500
1&
b1001 3
b10 1
#475000
0&
1*
1)
0(
#477500
1&
b1 4
#480000
0&
0+
0*
#482500
1&
b10 4
#485000
0&
1*
#487500
1&
b11 4
#490000
0&
1+
0)
#492500
1&
b100 4
#495000
0&
0+
0*
1(
#497500
1&
b101 4
#500000
0&
1+
1)
0(
#502500
1&
b110 4
#505000
0&
0)
1(
#507500
1&
b111 4
#510000
0&
0+
1*
0(
#512500
1&
b1000 4
b11 2
#515000
0&
1+
0*
#517500
1&
b1001 4
b11 1
#520000
0&
x+
x*
x)
x(
#522500
1&
b111 6
b1 5
b111111 0
b111111 .
b1000000 /
#525000
0&
#527500
1&
b100 6
b10 5
b111 0
0-
b1001000 /
#530000
0&
#532500
1&
b110 6
b11 5
b11111 0
b11111 .
b1101000 /
#535000
0&
#537500
1&
b11 6
b100 5
b11 0
b1101100 /
#540000
0&
#542500
1&
b1000 6
b101 5
b1111111 0
b10011 .
b11101100 /
#545000
0&
#547500
1&
b101 6
b110 5
b1111 0
b11 .
b11111100 /
#550000
0&
#552500
1&
b1001 6
b111 5
b11111111 0
b111111100 /
#555000
0&
#557500
1&
b10 6
b1000 5
b1 0
b1 .
b111111110 /
b100 2
#560000
0&
#562500
1&
b1 6
b1001 5
b0 0
b0 .
b111111111 /
b100 1
b0 2
#565000
0&
#567500
1&
1,
b0 1
b1 2
#570000
0&
#572500
1&
1-
0,
b0 /
b0 3
b0 4
b0 5
b0 7
b1 7
b10 7
b11 7
b100 7
b101 7
b110 7
b111 7
b1000 7
b1001 7
b1010 7
b1 1
b10 2
#575000
0&
0+
0*
0)
1(
#577500
1&
b1000 3
b10 1
#580000
0&
1)
0(
#582500
1&
b1 4
#585000
0&
0)
1(
#587500
1&
b10 4
#590000
0&
1*
1)
0(
#592500
1&
b11 4
#595000
0&
1+
0)
#597500
1&
b100 4
#600000
0&
0+
#602500
1&
b101 4
#605000
0&
1+
0*
1)
#607500
1&
b110 4
#610000
0&
1*
#612500
1&
b111 4
b11 2
#615000
0&
0*
0)
#617500
1&
b1000 4
b11 1
#620000
0&
x+
x*
x)
x(
#622500
1&
b100 6
b1 5
b111 0
b111 .
b1000 /
#625000
0&
#627500
1&
b1000 6
b10 5
b1111111 0
b1110111 .
b10001000 /
#630000
0&
#632500
1&
b110 6
b11 5
b11111 0
0-
b10101000 /
#635000
0&
#637500
1&
b11 6
b100 5
b11 0
b10101100 /
#640000
0&
#642500
1&
b10 6
b101 5
b1 0
b10101110 /
#645000
0&
#647500
1&
b101 6
b110 5
b1111 0
b10111110 /
#650000
0&
#652500
1&
b111 6
b111 5
b111111 0
b110111 .
b11111110 /
b100 2
#655000
0&
#657500
1&
b1 6
b1000 5
b0 0
b11111111 /
b100 1
b0 2
#660000
0&
#662500
1&
1,
b0 1
b1 2
#665000
0&
#667500
1&
1-
0,
b0 .
b0 /
b0 3
b0 4
b0 5
b0 7
b1 7
b10 7
b11 7
b100 7
b101 7
b110 7
b111 7
b1000 7
b1001 7
b1010 7
b1 1
b10 2
#670000
0&
1+
1*
0)
0(
#672500
1&
b11 3
b10 1
#675000
0&
0*
#677500
1&
b1 4
#680000
0&
0+
1*
#682500
1&
b10 4
b11 2
#685000
0&
1+
#687500
1&
b11 4
b11 1
#690000
0&
x+
x*
x)
x(
#692500
1&
b1 5
b1 /
#695000
0&
#697500
1&
b10 6
b10 5
b1 0
b11 /
b100 2
#700000
0&
#702500
1&
b11 6
b11 5
b11 0
b111 /
b100 1
b0 2
#705000
0&
#707500
1&
1,
b0 1
b1 2
#710000
0&
#712500
1&
0,
b0 /
b0 3
b0 4
b0 5
b0 7
b1 7
b10 7
b11 7
b100 7
b101 7
b110 7
b111 7
b1000 7
b1001 7
b1010 7
b1 1
b10 2
#715000
0&
0+
0*
1)
0(
#717500
1&
b100 3
b10 1
#720000
0&
1*
0)
#722500
1&
b1 4
#725000
0&
1+
0*
#727500
1&
b10 4
#730000
0&
0+
1)
#732500
1&
b11 4
b11 2
#735000
0&
1+
1*
0)
#737500
1&
b100 4
b11 1
#740000
0&
x+
x*
x)
x(
#742500
1&
b10 6
b1 5
b1 0
b1 .
b10 /
#745000
0&
#747500
1&
b1 6
b10 5
b0 0
b0 .
b11 /
#750000
0&
#752500
1&
b100 6
b11 5
b111 0
b100 .
b1011 /
b100 2
#755000
0&
#757500
1&
b11 6
b100 5
b11 0
b0 .
b1111 /
b100 1
b0 2
#760000
0&
#762500
1&
1,
b0 1
b1 2
#765000
0&
#767500
1&
0,
b0 /
b0 3
b0 4
b0 5
b0 7
b1 7
b10 7
b11 7
b100 7
b101 7
b110 7
b111 7
b1000 7
b1001 7
b1010 7
b1 1
b10 2
#770000
0&
1+
0*
1)
0(
#772500
1&
b101 3
b10 1
#775000
0&
0)
#777500
1&
b1 4
#780000
0&
0+
1)
#782500
1&
b10 4
#785000
0&
1+
1*
0)
#787500
1&
b11 4
#790000
0&
0*
1)
#792500
1&
b100 4
b11 2
#795000
0&
0+
1*
0)
#797500
1&
b101 4
b11 1
#800000
0&
x+
x*
x)
x(
#802500
1&
b1 6
b1 5
b0 0
b1 /
#805000
0&
#807500
1&
b100 6
b10 5
b111 0
b110 .
b1001 /
#810000
0&
#812500
1&
b11 6
b11 5
b11 0
b10 .
b1101 /
#815000
0&
#817500
1&
b101 6
b100 5
b1111 0
b11101 /
b100 2
#820000
0&
#822500
1&
b10 6
b101 5
b1 0
b0 .
b11111 /
b100 1
b0 2
#825000
0&
#827500
1&
1,
b0 1
b1 2
#830000
0&
#832500
1&
0,
b0 /
b0 3
b0 4
b0 5
b0 7
b1 7
b10 7
b11 7
b100 7
b101 7
b110 7
b111 7
b1000 7
b1001 7
b1010 7
b1 1
b10 2
#835000
0&
0+
1*
0)
1(
#837500
1&
b1010 3
b10 1
#840000
0&
1+
0*
#842500
1&
b1 4
#845000
0&
0+
1*
#847500
1&
b10 4
#850000
0&
1+
0*
0(
#852500
1&
b11 4
#855000
0&
0+
1*
#857500
1&
b100 4
#860000
0&
1+
1)
#862500
1&
b101 4
#865000
0&
0+
0*
0)
1(
#867500
1&
b110 4
#870000
0&
1*
1)
0(
#872500
1&
b111 4
#875000
0&
1+
0)
#877500
1&
b1000 4
#880000
0&
0+
0*
1)
#882500
1&
b1001 4
b11 2
#885000
0&
1+
#887500
1&
b1010 4
b11 1
#890000
0&
x+
x*
x)
x(
#892500
1&
b1001 6
b1 5
b11111111 0
b11111111 .
b100000000 /
#895000
0&
#897500
1&
b1010 6
b10 5
b111111111 0
b1100000000 /
#900000
0&
#902500
1&
b1 6
b11 5
b0 0
0-
b1100000001 /
#905000
0&
#907500
1&
b10 6
b100 5
b1 0
b1100000011 /
#910000
0&
#912500
1&
b111 6
b101 5
b111111 0
b1101000011 /
#915000
0&
#917500
1&
b1000 6
b110 5
b1111111 0
b1111111 .
b1111000011 /
#920000
0&
#922500
1&
b110 6
b111 5
b11111 0
b1111100011 /
#925000
0&
#927500
1&
b11 6
b1000 5
b11 0
b1111100111 /
#930000
0&
#932500
1&
b100 6
b1001 5
b111 0
b1111101111 /
b100 2
#935000
0&
#937500
1&
b101 6
b1010 5
b1111 0
b1111111111 /
b100 1
b0 2
#940000
0&
#942500
1&
1,
b0 1
b1 2
#945000
0&
#947500
1&
1-
0,
b0 .
b0 /
b0 3
b0 4
b0 5
b0 7
b1 7
b10 7
b11 7
b100 7
b101 7
b110 7
b111 7
b1000 7
b1001 7
b1010 7
b1 1
b10 2
#950000
0&
0+
1*
0)
1(
#952500
1&
b1010 3
b10 1
#955000
0&
0(
#957500
1&
b1 4
#960000
0&
1)
#962500
1&
b10 4
#965000
0&
1+
0*
0)
#967500
1&
b11 4
#970000
0&
0+
1(
#972500
1&
b100 4
#975000
0&
1+
1)
0(
#977500
1&
b101 4
#980000
0&
0+
#982500
1&
b110 4
#985000
0&
1+
1*
#987500
1&
b111 4
#990000
0&
0+
0)
1(
#992500
1&
b1000 4
#995000
0&
1+
0(
#997500
1&
b1001 4
b11 2
#1000000
0&
0*
1(
#1002500
1&
b1010 4
b11 1
#1005000
0&
x+
x*
x)
x(
#1007500
1&
b10 6
b1 5
b1 0
b1 .
b10 /
#1010000
0&
#1012500
1&
b110 6
b10 5
b11111 0
b11101 .
b100010 /
#1015000
0&
#1017500
1&
b1 6
b11 5
b0 0
0-
b100011 /
#1020000
0&
#1022500
1&
b1000 6
b100 5
b1111111 0
b1011100 .
b10100011 /
#1025000
0&
#1027500
1&
b101 6
b101 5
b1111 0
b10110011 /
#1030000
0&
#1032500
1&
b100 6
b110 5
b111 0
b10111011 /
#1035000
0&
#1037500
1&
b111 6
b111 5
b111111 0
b11100 .
b11111011 /
#1040000
0&
#1042500
1&
b1010 6
b1000 5
b111111111 0
b100000100 .
b1011111011 /
#1045000
0&
#1047500
1&
b11 6
b1001 5
b11 0
b1011111111 /
b100 2
#1050000
0&
#1052500
1&
b1001 6
b1010 5
b11111111 0
b100 .
b1111111111 /
b100 1
b0 2
#1055000
0&
#1057500
1&
1,
b0 1
b1 2
#1060000
0&
#1062500
1&
1-
0,
b0 .
b0 /
b0 3
b0 4
b0 5
b0 7
b1 7
b10 7
b11 7
b100 7
b101 7
b110 7
b111 7
b1000 7
b1001 7
b1010 7
b1 1
b10 2
#1065000
0&
0+
1*
0)
1(
#1067500
1&
b1010 3
b10 1
#1070000
0&
0*
1)
0(
#1072500
1&
b1 4
#1075000
0&
1+
0)
1(
#1077500
1&
b10 4
#1080000
0&
0+
1*
0(
#1082500
1&
b11 4
#1085000
0&
0*
1(
#1087500
1&
b100 4
#1090000
0&
1+
0(
#1092500
1&
b101 4
#1095000
0&
1*
1)
#1097500
1&
b110 4
#1100000
0&
0+
#1102500
1&
b111 4
#1105000
0&
0)
1(
#1107500
1&
b1000 4
#1110000
0&
1+
0(
#1112500
1&
b1001 4
b11 2
#1115000
0&
0*
1)
#1117500
1&
b1010 4
b11 1
#1120000
0&
x+
x*
x)
x(
#1122500
1&
b100 6
b1 5
b111 0
b111 .
b1000 /
#1125000
0&
#1127500
1&
b1001 6
b10 5
b11111111 0
b11110111 .
b100001000 /
#1130000
0&
#1132500
1&
b10 6
b11 5
b1 0
0-
b100001010 /
#1135000
0&
#1137500
1&
b1000 6
b100 5
b1111111 0
b1110111 .
b110001010 /
#1140000
0&
#1142500
1&
b1 6
b101 5
b0 0
b110001011 /
#1145000
0&
#1147500
1&
b111 6
b110 5
b111111 0
b110111 .
b111001011 /
#1150000
0&
#1152500
1&
b110 6
b111 5
b11111 0
b10111 .
b111101011 /
#1155000
0&
#1157500
1&
b1010 6
b1000 5
b111111111 0
b10100 .
b1111101011 /
#1160000
0&
#1162500
1&
b11 6
b1001 5
b11 0
b1111101111 /
b100 2
#1165000
0&
#1167500
1&
b101 6
b1010 5
b1111 0
b100 .
b1111111111 /
b100 1
b0 2
#1170000
0&
#1172500
1&
1,
b0 1
b1 2
#1175000
0&
#1177500
1&
1-
0,
b0 .
b0 /
b0 3
b0 4
b0 5
b0 7
b1 7
b10 7
b11 7
b100 7
b101 7
b110 7
b111 7
b1000 7
b1001 7
b1010 7
b1 1
b10 2
#1180000
0&
0+
1*
1)
0(
#1182500
1&
b110 3
b10 1
#1185000
0&
0*
#1187500
1&
b1 4
#1190000
0&
1+
#1192500
1&
b10 4
#1195000
0&
0)
#1197500
1&
b11 4
#1200000
0&
1*
#1202500
1&
b100 4
#1205000
0&
0+
#1207500
1&
b101 4
b11 2
#1210000
0&
1)
#1212500
1&
b110 4
b11 1
#1215000
0&
x+
x*
x)
x(
#1217500
1&
b100 6
b1 5
b111 0
b111 .
b1000 /
#1220000
0&
#1222500
1&
b101 6
b10 5
b1111 0
b11000 /
#1225000
0&
#1227500
1&
b1 6
b11 5
b0 0
0-
b11001 /
#1230000
0&
#1232500
1&
b11 6
b100 5
b11 0
b11 .
b11101 /
#1235000
0&
#1237500
1&
b10 6
b101 5
b1 0
b1 .
b11111 /
b100 2
#1240000
0&
#1242500
1&
b110 6
b110 5
b11111 0
b0 .
b111111 /
b100 1
b0 2
#1245000
0&
#1247500
1&
1,
b0 1
b1 2
#1250000
0&
#1252500
1&
1-
0,
b0 /
b0 3
b0 4
b0 5
b0 7
b1 7
b10 7
b11 7
b100 7
b101 7
b110 7
b111 7
b1000 7
b1001 7
b1010 7
b1 1
b10 2
#1255000
0&
0+
1*
0)
1(
#1257500
1&
b1010 3
b10 1
#1260000
0&
0*
1)
0(
#1262500
1&
b1 4
#1265000
0&
1+
1*
#1267500
1&
b10 4
#1270000
0&
0+
0)
1(
#1272500
1&
b11 4
#1275000
0&
0(
#1277500
1&
b100 4
#1280000
0&
1+
0*
1(
#1282500
1&
b101 4
#1285000
0&
0(
#1287500
1&
b110 4
#1290000
0&
1)
#1292500
1&
b111 4
#1295000
0&
0+
1*
#1297500
1&
b1000 4
#1300000
0&
1+
0)
#1302500
1&
b1001 4
b11 2
#1305000
0&
0+
0*
1(
#1307500
1&
b1010 4
b11 1
#1310000
0&
x+
x*
x)
x(
#1312500
1&
b100 6
b1 5
b111 0
b111 .
b1000 /
#1315000
0&
#1317500
1&
b111 6
b10 5
b111111 0
b110111 .
b1001000 /
#1320000
0&
#1322500
1&
b1010 6
b11 5
b111111111 0
b110110111 .
b1001001000 /
#1325000
0&
#1327500
1&
b10 6
b100 5
b1 0
0-
b1001001010 /
#1330000
0&
#1332500
1&
b1001 6
b101 5
b11111111 0
b10110111 .
b1101001010 /
#1335000
0&
#1337500
1&
b1 6
b110 5
b0 0
b1101001011 /
#1340000
0&
#1342500
1&
b101 6
b111 5
b1111 0
b1101011011 /
#1345000
0&
#1347500
1&
b110 6
b1000 5
b11111 0
b1101111011 /
#1350000
0&
#1352500
1&
b11 6
b1001 5
b11 0
b1101111111 /
b100 2
#1355000
0&
#1357500
1&
b1000 6
b1010 5
b1111111 0
b110111 .
b1111111111 /
b100 1
b0 2
#1360000
0&
#1362500
1&
1,
b0 1
b1 2
#1365000
0&
#1367500
1&
1-
0,
b0 .
b0 /
b0 3
b0 4
b0 5
b0 7
b1 7
b10 7
b11 7
b100 7
b101 7
b110 7
b111 7
b1000 7
b1001 7
b1010 7
b1 1
b10 2
#1370000
0&
1+
1*
0)
0(
#1372500
1&
b11 3
b10 1
#1375000
0&
0+
#1377500
1&
b1 4
#1380000
0&
1+
#1382500
1&
b10 4
b11 2
#1385000
0&
0*
#1387500
1&
b11 4
b11 1
#1390000
0&
x+
x*
x)
x(
#1392500
1&
b10 6
b1 5
b1 0
b1 .
b10 /
#1395000
0&
#1397500
1&
b11 6
b10 5
b11 0
b110 /
b100 2
#1400000
0&
#1402500
1&
b1 6
b11 5
b0 0
b0 .
b111 /
b100 1
b0 2
#1405000
0&
#1407500
1&
1,
b0 1
b1 2
#1410000
0&
#1412500
1&
0,
b0 /
b0 3
b0 4
b0 5
b0 7
b1 7
b10 7
b11 7
b100 7
b101 7
b110 7
b111 7
b1000 7
b1001 7
b1010 7
b1 1
b10 2
#1415000
0&
0+
0*
1)
0(
#1417500
1&
b100 3
b10 1
#1420000
0&
1*
0)
#1422500
1&
b1 4
#1425000
0&
0*
1)
#1427500
1&
b10 4
#1430000
0&
1+
1*
0)
#1432500
1&
b11 4
b11 2
#1435000
0&
0*
#1437500
1&
b100 4
b11 1
#1440000
0&
x+
x*
x)
x(
#1442500
1&
b10 6
b1 5
b1 0
b1 .
b10 /
#1445000
0&
#1447500
1&
b100 6
b10 5
b111 0
b101 .
b1010 /
#1450000
0&
#1452500
1&
b11 6
b11 5
b11 0
b1 .
b1110 /
b100 2
